ShockMaterials/Materials.py
ShockMaterials/__init__.py
ShockMaterials/example.py
ShockMaterials-0.0.1.dist-info/METADATA
ShockMaterials-0.0.1.dist-info/WHEEL
ShockMaterials-0.0.1.dist-info/top_level.txt
ShockMaterials-0.0.1.dist-info/RECORD
